haiku_mup/__init__.py
haiku_mup/ctx.py
haiku_mup/init.py
haiku_mup/module.py
haiku_mup/mup.py
haiku_mup-0.1.5.dist-info/LICENSE
haiku_mup-0.1.5.dist-info/WHEEL
haiku_mup-0.1.5.dist-info/METADATA
haiku_mup-0.1.5.dist-info/RECORD
