Metadata-Version: 2.1
Name: haiku-mup
Version: 0.1.5
Summary: A simple port of μP  to Haiku/JAX.
License: MIT
Author: Davis Yoshida
Author-email: dyoshida@ttic.edu
Requires-Python: >=3.7,<4.0
Classifier: License :: OSI Approved :: MIT License
Classifier: Programming Language :: Python :: 3
Classifier: Programming Language :: Python :: 3.10
Classifier: Programming Language :: Python :: 3.7
Classifier: Programming Language :: Python :: 3.8
Classifier: Programming Language :: Python :: 3.9
Requires-Dist: dm-haiku (>=0.0.6,<0.0.7)
Requires-Dist: jax (>=0.3.7,<0.4.0)
Requires-Dist: optax (>=0.1.2,<0.2.0)
